anyscale/__init__.py
anyscale/anyscale-cloud-setup-gcp-oa.yaml
anyscale/anyscale-cloud-setup-gcp.yaml
anyscale/anyscale-cloud-setup-oa.yaml
anyscale/anyscale-cloud-setup.yaml
anyscale/anyscale_schema.json
anyscale/api.py
anyscale/authenticate.py
anyscale/aws_iam_policies.py
anyscale/cli_logger.py
anyscale/cloud_resource.py
anyscale/cloud_utils.py
anyscale/cluster.py
anyscale/cluster_compute.py
anyscale/cluster_env.py
anyscale/component_activity_util.py
anyscale/conf.py
anyscale/connect.py
anyscale/feature_flags.py
anyscale/fingerprint.py
anyscale/gcp_verification.py
anyscale/integrations.py
anyscale/links.py
anyscale/memorydb_supported_zones.json
anyscale/project_utils.py
anyscale/scripts.py
anyscale/snapshot.py
anyscale/tables.py
anyscale/telemetry.py
anyscale/util.py
anyscale/version.py
anyscale/_private/anyscale_client/README.md
anyscale/_private/anyscale_client/__init__.py
anyscale/_private/anyscale_client/anyscale_client.py
anyscale/_private/anyscale_client/common.py
anyscale/_private/anyscale_client/fake_anyscale_client.py
anyscale/_private/docgen/README.md
anyscale/_private/docgen/__main__.py
anyscale/_private/docgen/api.md
anyscale/_private/docgen/generator.py
anyscale/_private/docgen/generator_legacy.py
anyscale/_private/docgen/models.md
anyscale/_private/models/__init__.py
anyscale/_private/models/image_uri.py
anyscale/_private/models/model_base.py
anyscale/_private/sdk/__init__.py
anyscale/_private/sdk/base_sdk.py
anyscale/_private/sdk/timer.py
anyscale/_private/utils/__init__.py
anyscale/_private/utils/progress_util.py
anyscale/_private/workload/__init__.py
anyscale/_private/workload/workload_config.py
anyscale/_private/workload/workload_sdk.py
anyscale/aggregated_instance_usage/__init__.py
anyscale/aggregated_instance_usage/commands.py
anyscale/aggregated_instance_usage/models.py
anyscale/aggregated_instance_usage/_private/aggregated_instance_usage_sdk.py
anyscale/anyscale_pydantic/HISTORY.md
anyscale/anyscale_pydantic/LICENSE
anyscale-0.26.81.dist-info/licenses/LICENSE
anyscale-0.26.81.dist-info/licenses/NOTICE
anyscale-0.26.81.dist-info/METADATA
anyscale-0.26.81.dist-info/WHEEL
anyscale-0.26.81.dist-info/entry_points.txt
anyscale-0.26.81.dist-info/top_level.txt
anyscale-0.26.81.dist-info/RECORD
